HISTORY.rst
LICENSE
MANIFEST.in
README.rst
setup.py
django_oidc.egg-info/PKG-INFO
django_oidc.egg-info/SOURCES.txt
django_oidc.egg-info/dependency_links.txt
django_oidc.egg-info/not-zip-safe
django_oidc.egg-info/requires.txt
django_oidc.egg-info/top_level.txt
djangooidc/__init__.py
djangooidc/backends.py
djangooidc/oidc.py
djangooidc/urls.py
djangooidc/views.py
djangooidc/templates/djangooidc/base.html
djangooidc/templates/djangooidc/error.html
djangooidc/templates/djangooidc/login.html