Metadata-Version: 1.1
Name: django-oidc
Version: 0.1.4
Summary: A Django OpenID Connect (OIDC) authentication backend
Home-page: https://github.com/marcanpilami/django-oidc
Author: Marc-Antoine Gouillart
Author-email: marsu_pilami@msn.com
License: Apache Software License
Keywords: repo_name
Platform: UNKNOWN
Classifier: Environment :: Web Environment
Classifier: Development Status :: 5 - Production/Stable
Classifier: Framework :: Django
Classifier: Intended Audience :: Developers
Classifier: License :: OSI Approved :: Apache Software License
Classifier: Operating System :: OS Independent
Classifier: Natural Language :: English
Classifier: Programming Language :: Python :: 2.7
